optgraphstate/__init__.py
optgraphstate/graph_tools.py
optgraphstate/utils.py
optgraphstate/visualization.py
optgraphstate-0.3.1.dist-info/LICENSE
optgraphstate-0.3.1.dist-info/METADATA
optgraphstate-0.3.1.dist-info/WHEEL
optgraphstate-0.3.1.dist-info/top_level.txt
optgraphstate-0.3.1.dist-info/RECORD
