Metadata-Version: 2.1
Name: optgraphstate
Version: 0.3.1
Summary: Graph-theoretical optimization of fusion-based graph state generation
Home-page: https://github.com/seokhyung-lee/OptGraphState
Author: Seok-Hyung Lee
Author-email: sh.lee1524@gmail.com
Classifier: Programming Language :: Python :: 3
Classifier: License :: OSI Approved :: MIT License
Classifier: Operating System :: OS Independent
License-File: LICENSE
